{"type":"1","days":[["1","2","3","4","5"],["6","0"]],"times":[["{\"hour\":6,\"minute\":23}","{\"hour\":7,\"minute\":6}","{\"hour\":7,\"minute\":28}","{\"hour\":7,\"minute\":49}","{\"hour\":8,\"minute\":11}","{\"hour\":8,\"minute\":32}","{\"hour\":8,\"minute\":54}","{\"hour\":9,\"minute\":37}","{\"hour\":9,\"minute\":58}","{\"hour\":11,\"minute\":0}","{\"hour\":11,\"minute\":40}","{\"hour\":12,\"minute\":21}","{\"hour\":13,\"minute\":2}","{\"hour\":13,\"minute\":43}","{\"hour\":14,\"minute\":24}","{\"hour\":15,\"minute\":5}","{\"hour\":15,\"minute\":46}","{\"hour\":16,\"minute\":11}","{\"hour\":16,\"minute\":31}","{\"hour\":16,\"minute\":56}","{\"hour\":17,\"minute\":11}","{\"hour\":17,\"minute\":37}","{\"hour\":17,\"minute\":57}","{\"hour\":18,\"minute\":22}","{\"hour\":19,\"minute\":5}","{\"hour\":19,\"minute\":48}","{\"hour\":20,\"minute\":54}","{\"hour\":21,\"minute\":28}","{\"hour\":22,\"minute\":50}"],["{\"hour\":6,\"minute\":25}","{\"hour\":7,\"minute\":19}","{\"hour\":7,\"minute\":47}","{\"hour\":8,\"minute\":14}","{\"hour\":8,\"minute\":41}","{\"hour\":9,\"minute\":9}","{\"hour\":9,\"minute\":36}","{\"hour\":11,\"minute\":0}","{\"hour\":11,\"minute\":26}","{\"hour\":11,\"minute\":57}","{\"hour\":12,\"minute\":26}","{\"hour\":12,\"minute\":52}","{\"hour\":13,\"minute\":23}","{\"hour\":14,\"minute\":18}","{\"hour\":14,\"minute\":49}","{\"hour\":15,\"minute\":15}","{\"hour\":15,\"minute\":44}","{\"hour\":16,\"minute\":15}","{\"hour\":16,\"minute\":39}","{\"hour\":17,\"minute\":7}","{\"hour\":17,\"minute\":37}","{\"hour\":18,\"minute\":29}","{\"hour\":20,\"minute\":34}","{\"hour\":21,\"minute\":33}","{\"hour\":21,\"minute\":56}","{\"hour\":22,\"minute\":55}"]],"spetial_days":[],"spetial_times":[]}